ADCT/DataHandler.py
ADCT/DataOBJ.py
ADCT-1.1.2.dist-info/LICENSE
ADCT-1.1.2.dist-info/METADATA
ADCT-1.1.2.dist-info/WHEEL
ADCT-1.1.2.dist-info/top_level.txt
ADCT-1.1.2.dist-info/RECORD
